feplot/__init__.py
feplot/_helpers.py
feplot/_plotter.py
feplot/_xdmf.py
feplot/icons/feplot.png
feplot/icons/play.png
feplot/icons/stop.png
feplot-0.1.13.dist-info/LICENSE
feplot-0.1.13.dist-info/METADATA
feplot-0.1.13.dist-info/WHEEL
feplot-0.1.13.dist-info/top_level.txt
feplot-0.1.13.dist-info/RECORD
