Metadata-Version: 2.1
Name: feplot
Version: 0.1.13
Summary: A visualization tool for FElupe
Author: Mohamed ZAARAOUI
Author-email: mohamed.zaaraoui.999@gmail.com
License: GNU GENERAL PUBLIC LICENSE
Project-URL: homepage, https://feplot.readthedocs.io/en/latest
Project-URL: code, https://github.com/ZAARAOUI999/feplot
Project-URL: issues, https://github.com/ZAARAOUI999/feplot/issues
Project-URL: repository, https://github.com/ZAARAOUI999/feplot.git
Keywords: python,constitution,scientific-computing,fem,finite-elements-analysis,hyperelasticity
Classifier: Programming Language :: Python
Classifier: Intended Audience :: Science/Research
Classifier: License :: OSI Approved :: GNU General Public License v3 or later (GPLv3+)
Classifier: Operating System :: OS Independent
Classifier: Programming Language :: Python :: 3
Classifier: Topic :: Scientific/Engineering
Classifier: Topic :: Utilities
Requires-Python: >=3.6
License-File: LICENSE
Requires-Dist: numpy
Requires-Dist: pyvista
Requires-Dist: pyvistaqt
Requires-Dist: meshio
Requires-Dist: felupe
